json_remap_engine/__init__.py
json_remap_engine/jsonpath_compat.py
json_remap_engine/path_utils.py
json_remap_engine/py.typed
json_remap_engine/rules.py
json_remap_engine/safe_filter.py
json_remap_engine/transformer.py
json_remap_engine-0.2.0.dist-info/METADATA
json_remap_engine-0.2.0.dist-info/WHEEL
json_remap_engine-0.2.0.dist-info/licenses/LICENSE
json_remap_engine-0.2.0.dist-info/RECORD
