Metadata-Version: 2.4
Name: json-remap-engine
Version: 0.2.0
Summary: JSONPath-driven remapping engine that produces JSON Patch operations.
Project-URL: Homepage, https://github.com/earada/json-remap-engine
Project-URL: Repository, https://github.com/earada/json-remap-engine
Author-email: Eduardo Arada <eduardo.arada@gamil.com>
License: MIT
License-File: LICENSE
Keywords: json,jsonpatch,jsonpath,rules-engine,transform
Classifier: Development Status :: 3 - Alpha
Classifier: Intended Audience :: Developers
Classifier: License :: OSI Approved :: MIT License
Classifier: Programming Language :: Python :: 3
Classifier: Programming Language :: Python :: 3.11
Classifier: Programming Language :: Python :: 3.12
Classifier: Programming Language :: Python :: 3.13
Requires-Python: >=3.11
Requires-Dist: jsonpath-ng>=1.7.0
Provides-Extra: dev
Requires-Dist: pytest>=8.0.0; extra == 'dev'
